scrapyard/__init__.py
scrapyard-0.0.0.dist-info/METADATA
scrapyard-0.0.0.dist-info/WHEEL
scrapyard-0.0.0.dist-info/top_level.txt
scrapyard-0.0.0.dist-info/RECORD
