Metadata-Version: 2.1
Name: scrapyard
Version: 0.0.0
Summary: Dummy
Home-page: UNKNOWN
Author: Samoxiaki
Author-email: samoxiaki@yahoo.com
License: UNKNOWN
Platform: UNKNOWN
